camguard/__init__.py
camguard/__main__.py
camguard/bridge_api.py
camguard/bridge_impl.py
camguard/camguard.py
camguard/camguard_settings.py
camguard/dummy_cam.py
camguard/dummy_gdrive_storage.py
camguard/dummy_gpio_sensor.py
camguard/dummy_mail_client.py
camguard/dummy_mail_server.py
camguard/dummy_network_device_detector.py
camguard/exceptions.py
camguard/extended_enum.py
camguard/file_storage_settings.py
camguard/gdrive_storage.py
camguard/generic_mail_client.py
camguard/mail_client_settings.py
camguard/motion_detector_settings.py
camguard/motion_handler_settings.py
camguard/network_device_detector_settings.py
camguard/nmap_device_detector.py
camguard/raspi_cam.py
camguard/raspi_gpio_sensor.py
camguard/settings.py
camguard/certs/__init__.py
camguard/certs/dummy_mail.cert
camguard/certs/dummy_mail.key
camguard-1.1.0b0.dist-info/LICENSE
camguard-1.1.0b0.dist-info/METADATA
camguard-1.1.0b0.dist-info/WHEEL
camguard-1.1.0b0.dist-info/entry_points.txt
camguard-1.1.0b0.dist-info/top_level.txt
camguard-1.1.0b0.dist-info/RECORD
