Metadata-Version: 2.1
Name: camguard
Version: 1.1.0b0
Summary: camguard - home surveillance system
Home-page: https://camguard.readthedocs.io/
Author: matt-hires
Author-email: camguard@matt-hires.at
License: GNU General Public License v3 (GPLv3)
Project-URL: Bug Tracker, https://github.com/matt-hires/camguard/issues
Project-URL: Documentation, https://camguard.readthedocs.io/
Project-URL: Source Code, https://github.com/matt-hires/camguard
Platform: UNKNOWN
Classifier: Programming Language :: Python :: 3 :: Only
Classifier: Programming Language :: Python :: 3.7
Classifier: Programming Language :: Python :: 3.8
Classifier: Programming Language :: Python :: 3.9
Classifier: License :: OSI Approved :: GNU General Public License v3 (GPLv3)
Classifier: Operating System :: POSIX :: Linux
Classifier: Development Status :: 4 - Beta
Requires-Python: >=3.7.3
License-File: LICENSE
Requires-Dist: gpiozero
Requires-Dist: python-daemon
Requires-Dist: pid
Requires-Dist: pyyaml
Requires-Dist: google-api-python-client
Requires-Dist: google-auth-httplib2
Requires-Dist: google-auth-oauthlib
Requires-Dist: aiosmtpd
Provides-Extra: debug
Requires-Dist: debugpy ; extra == 'debug'
Provides-Extra: dev
Requires-Dist: autopep8 ; extra == 'dev'
Requires-Dist: coverage ; extra == 'dev'
Requires-Dist: tox ; extra == 'dev'
Requires-Dist: debugpy ; extra == 'dev'
Requires-Dist: docutils (<0.18) ; extra == 'dev'
Requires-Dist: sphinx ; extra == 'dev'
Requires-Dist: sphinx-autobuild ; extra == 'dev'
Requires-Dist: sphinx-rtd-theme ; extra == 'dev'
Requires-Dist: sphinxcontrib-autoprogram ; extra == 'dev'
Requires-Dist: build ; extra == 'dev'
Requires-Dist: twine ; extra == 'dev'
Provides-Extra: raspi
Requires-Dist: RPi.GPIO ; extra == 'raspi'
Requires-Dist: picamera ; extra == 'raspi'
